misc_utils/__init__.py
misc_utils/classes.py
misc_utils/decorators.py
misc_utils/misc_utils.py
misc_utils/template.py
misc_utils/version.py
utils_misc-0.1.0.dist-info/LICENSE
utils_misc-0.1.0.dist-info/METADATA
utils_misc-0.1.0.dist-info/WHEEL
utils_misc-0.1.0.dist-info/top_level.txt
utils_misc-0.1.0.dist-info/RECORD
