Metadata-Version: 2.1
Name: utils-misc
Version: 0.1.0
Summary: Misc_Utils - Misc system and time utilities for python projects
Home-page: https://github.com/misads/misc_utils
Author: Haoyu Xu
Author-email: xuhaoyu@tju.edu.cn
License: MIT
Platform: UNKNOWN
Classifier: Development Status :: 3 - Alpha
Classifier: Programming Language :: Python :: 3
Classifier: License :: OSI Approved :: MIT License
Classifier: Operating System :: OS Independent
Requires-Python: >=3.5
Requires-Dist: numpy
